{"4rpdzuvxFno5GVSBj7yJ0Q==":"hail%20white-90x26.png","z/7iuQL0H1epIWLnjG0X1A==":"hail%20png%201500-240x69.png","MRzef4+CUZ8BgD7j90hkPA==":"hail%20png%201500-240x69.png","IxXcyocx9Ng7RABv11yewA==":"hail%20banner-1920x955.png","Z3KRSooesM29uQALCoe9ng==":"hail%20banner-1920x955.png","f/Nh0hzDjqb4ZCI0g7f/xg==":"hail%20background-1920x955.png","cWWBXWE3PkN7UGU7WptdVQ==":"hail%20communting-1062x1062.png","XRRtCMmAT1ZPY5h2L1HBHw==":"hail%20for%20logistics-1062x1062.png","eXNU9Fuf3VnnNvfs/Ydi8g==":"about%201-640x464.png","qPEHrlOYIyl3IeU/tkxTEw==":"hail%20driver%20fair%20rate-676x676.png","NhYz/EtL/7ebR8MAW87nig==":"hail%20driver%20form-676x676.png","cjpLiTzvVH193yjnahG8+w==":"hail%20driver%20choice-676x676.png","/n20RyJOWpDiCa1WhEQp2Q==":"hl%20promo1%20-900x900.png","q8qowpPf6TA8yi9V8cod3Q==":"hl%20promo1%20-900x900.png","HEpptX6khAgadiLJUN0uzA==":"hail%20mock%20up1-1048x699.png","y/2iwKn5jFuXSLHKJnVA+w==":"hali%20banner%202-1920x955.png","tWa9gRJvkSq4OfT4pfKLnA==":"hali%20banner%202-1920x955.png","PI+wfzp4kpewOO4IimuuUg==":"icon-512x341.png","u0Ye/Kq/6n617wDUJEbb9A==":"icon-90x60.png","1wivyIE1V5rnA5U9Vn4fJQ==":"up2-225x250.jpeg","1Pcl37wWrI3wpFbyqy4QMg==":"up3-225x250.jpg","f3s1JO0KqCeL+FEzRGb/gg==":"up4-225x250.jpg","qnD4YiZPAx2ht/7mew+CIg==":"000000001-676x676.png","be6G41epC2qDPECQC9N1kg==":"00000001-676x676.png","69OESZky0EzKm5OXD2JY+g==":"0909090-676x676.png","G+x0+Zo81EtoFngMYpVQAg==":"banner%201-900x600.jpg","24VzVc1SJUcppnRYbLIKJA==":"00000-900x600.jpg","J8AWL1lIaMSSTg6BXW2y1A==":"haill%20apppp-1048x1048.png","nmqHCDXa0rf4qHffVRBMOg==":"000000000000000000000-1062x1062.png","lbc+kBzZKlBa8/3BLP8Mpw==":"iiii-1062x1062.png","+KRqnJViVc7f+v2miPDoMw==":"000000000000000000000-1-1062x1062.png","yKaqa0UsPn6TZkyGKf38Gw==":"iiii-1-1062x1062.png","4R1ReDPwP9WUijBLX1vr2g==":"iiii-2-1062x1062.png","VaCZaQJDNG3NjR2pXnEtQQ==":"iiii-3-1062x1062.png","q1dHDWERbVuWsihFP+JSxQ==":"hail%20commuting-1920x955.png","7cXI9HyOEGyyvP4p9nQeXQ==":"===-1920x955.png","0Nw3AqhU5J8fa1/ovaV1MA==":"hail%20driver%20fair%20rate-676x676.png","4BW7SFMdSlHIQ+LtvFZ2QQ==":"hail%20driver%20form-676x676.png","Q2F5D+w8Hc0b65vFrxwT9A==":"hail%20driver%20choice-676x676.png","RD7jOEmrPKr6sQzQuIk/7A==":"hail%20driver%20fair%20rate-676x676.png","HAqYsEZvJjYqIdJiOMFhJA==":"hail%20driver%20form-676x676.png","OQDm0gOb/DHOQlVdSjh8Ag==":"hail%20driver%20choice-676x676.png","SYbFKND8u7EmcXpFjoDf0g==":"hail%20driver%20fair%20rate-676x676.png","EVeD4L08kTjMibyRs5memQ==":"hail%20white-90x26.png","md+lxAo/ZopAn45Nyz9h5w==":"hail%20driver%20fair%20rate-512x512.png","Rvwl7Qny9fR6k2o0ml/y6Q==":"hail%20driver%20form-512x512.png","Uz7XQohdB78VILEd8Sng8g==":"hail%20driver%20choice-512x512.png","jyH0VE36Aec1lax+byGrVg==":"hail%20driver%20fair%20rate-512x512.png","AuvvtK3x1pA+bxhDCeyl2g==":"hail%20driver%20form-512x512.png","F+CaKj/NmLMAWyylphRPkw==":"hail%20driver%20choice-512x512.png"}